o3r_docker_manager/__init__.py
o3r_docker_manager/o3r_docker_manager.py
o3r_docker_manager/oem_logging.py
o3r_docker_manager-0.0.9.dist-info/LICENSE
o3r_docker_manager-0.0.9.dist-info/METADATA
o3r_docker_manager-0.0.9.dist-info/WHEEL
o3r_docker_manager-0.0.9.dist-info/entry_points.txt
o3r_docker_manager-0.0.9.dist-info/top_level.txt
o3r_docker_manager-0.0.9.dist-info/RECORD
