Metadata-Version: 2.1
Name: o3r-docker-manager
Version: 0.0.9
Summary: O3R docker deployment utilities
Author: ifm gmbh
License-File: LICENSE
Requires-Dist: pyyaml
Requires-Dist: scp
Requires-Dist: ifm3dpy
